surorm/__init__.py
surorm/manager.py
surorm/migrations.py
surorm/query/__init__.py
surorm/query/alias.py
surorm/query/create.py
surorm/query/data_model.py
surorm/query/define.py
surorm/query/delete.py
surorm/query/function.py
surorm/query/graph.py
surorm/query/info.py
surorm/query/mixins.py
surorm/query/operation.py
surorm/query/relation.py
surorm/query/remove.py
surorm/query/select.py
surorm/query/transaction.py
surorm/query/types.py
surorm/query/update.py
surorm/query/utils.py
surorm/query/variable.py
surorm/response.py
surorm/serializers.py
surorm/settings.py
surorm/tester.py
surorm/utils.py
surorm-0.0.5.dist-info/METADATA
surorm-0.0.5.dist-info/WHEEL
surorm-0.0.5.dist-info/RECORD
